kling3_ai/__init__.py
kling3_ai-0.1.0.dist-info/licenses/LICENSE
kling3_ai-0.1.0.dist-info/METADATA
kling3_ai-0.1.0.dist-info/WHEEL
kling3_ai-0.1.0.dist-info/top_level.txt
kling3_ai-0.1.0.dist-info/RECORD
