Metadata-Version: 2.4
Name: kling3-ai
Version: 0.1.0
Summary: Kling 3 AI - Next-generation AI video creation platform with 4K resolution and intelligent motion control
Home-page: https://kling3.net
Author-email: Kling3 Team <contact@kling3.net>
License: MIT
Project-URL: Homepage, https://kling3.net
Project-URL: Documentation, https://kling3.net
Project-URL: Website, https://kling3.net
Keywords: kling3,kling3-ai,ai-video,video-generation,text-to-video,image-to-video,4k-video,artificial-intelligence,content-creation,cinematic-ai
Classifier: Development Status :: 4 - Beta
Classifier: Intended Audience :: Developers
Classifier: Intended Audience :: End Users/Desktop
Classifier: License :: OSI Approved :: MIT License
Classifier: Programming Language :: Python :: 3
Classifier: Programming Language :: Python :: 3.9
Classifier: Programming Language :: Python :: 3.10
Classifier: Programming Language :: Python :: 3.11
Classifier: Programming Language :: Python :: 3.12
Classifier: Topic :: Multimedia :: Video
Classifier: Topic :: Scientific/Engineering :: Artificial Intelligence
Classifier: Topic :: Multimedia :: Graphics :: 3D Rendering
Requires-Python: >=3.9
License-File: LICENSE
Dynamic: home-page
Dynamic: license-file
Dynamic: requires-python
